setup.cfg
setup.py
test/test_htmlpurifier.py
thorium_htmlpurifier/__init__.py
thorium_htmlpurifier.egg-info/PKG-INFO
thorium_htmlpurifier.egg-info/SOURCES.txt
thorium_htmlpurifier.egg-info/dependency_links.txt
thorium_htmlpurifier.egg-info/not-zip-safe
thorium_htmlpurifier.egg-info/requires.txt
thorium_htmlpurifier.egg-info/top_level.txt