Metadata-Version: 1.0
Name: thorium-htmlpurifier
Version: 0.1.1
Summary: HTML Purifier validation for Thorium
Home-page: https://github.com/meunierd/thorium_htmlpurifier/
Author: Devon Meunier
Author-email: devon@eventmobi.com
License: UNKNOWN
Platform: UNKNOWN
